{
  "$schema": "https://developer.microsoft.com/json-schemas/fabric/item/report/definition/visualContainer/1.3.0/schema.json",
  "name": "55e342f1b188a7651606",
  "position": {
    "x": 10.021352313167259,
    "y": 0,
    "z": 0,
    "height": 279.6868327402135,
    "width": 603.10320284697514
  },
  "visual": {
    "visualType": "tableEx",
    "query": {
      "queryState": {
        "Values": {
          "projections": [
            {
              "field": {
                "Column": {
                  "Expression": {
                    "SourceRef": {
                      "Entity": "Health Status"
                    }
                  },
                  "Property": "Code"
                }
              },
              "queryRef": "Health Status.Code"
            },
            {
              "field": {
                "Column": {
                  "Expression": {
                    "SourceRef": {
                      "Entity": "Health Status"
                    }
                  },
                  "Property": "Status"
                }
              },
              "queryRef": "Health Status.Status"
            }
          ]
        }
      }
    },
    "drillFilterOtherVisuals": true
  }
}